{
  "project_info": {
    "project_number": "124903687224",
    "project_id": "weather-app-13015",
    "storage_bucket": "weather-app-13015.appspot.com"
  },
  "client": [
    {
      "client_info": {
        "mobilesdk_app_id": "1:124903687224:android:c476196db3eb2ebab152cd",
        "android_client_info": {
          "package_name": "com.example.weather_app"
        }
      },
      "oauth_client": [
        {
          "client_id": "124903687224-ho0l315ggrn458t0jopebeg8gs0trdcj.apps.googleusercontent.com",
          "client_type": 3
        }
      ],
      "api_key": [
        {
          "current_key": "AIzaSyAgehQ6eg28wDMivmuVV8mVN3T9BKD8VdE"
        }
      ],
      "services": {
        "appinvite_service": {
          "other_platform_oauth_client": [
            {
              "client_id": "124903687224-ho0l315ggrn458t0jopebeg8gs0trdcj.apps.googleusercontent.com",
              "client_type": 3
            }
          ]
        }
      }
    }
  ],
  "configuration_version": "1"
}